L3MinioCache/CacheInterface.py
L3MinioCache/FileL2Cache.py
L3MinioCache/MinioL3Cache.py
L3MinioCache/PickleL2Cache.py
L3MinioCache/__init__.py
Python_Minio_L3_Cache-0.1.4.dist-info/LICENSE
Python_Minio_L3_Cache-0.1.4.dist-info/METADATA
Python_Minio_L3_Cache-0.1.4.dist-info/WHEEL
Python_Minio_L3_Cache-0.1.4.dist-info/top_level.txt
Python_Minio_L3_Cache-0.1.4.dist-info/RECORD
