Metadata-Version: 2.1
Name: Python-Minio-L3-Cache
Version: 0.1.4
Summary: Simple object-store caching helper library for python3. It uses Pickle for L2 cache and Minio as L3 cache.
Home-page: https://github.com/christinoleo/Python-Minio-L3-Cache/
Author: Leonardo Christino
Author-email: leomilho@gmail.com
License: MIT
Platform: UNKNOWN
